hiviper/__init__.py
hiviper/viper_ascii.py
hiviper-0.1.0.dist-info/METADATA
hiviper-0.1.0.dist-info/WHEEL
hiviper-0.1.0.dist-info/entry_points.txt
hiviper-0.1.0.dist-info/top_level.txt
hiviper-0.1.0.dist-info/RECORD
