Metadata-Version: 2.4
Name: hiviper
Version: 0.1.0
Summary: Viper ASCII Art
Requires-Python: >=3.13
